pywren_ibm_cloud/__init__.py
pywren_ibm_cloud/config.py
pywren_ibm_cloud/executor.py
pywren_ibm_cloud/future.py
pywren_ibm_cloud/invoker.py
pywren_ibm_cloud/plots.py
pywren_ibm_cloud/tests.py
pywren_ibm_cloud/utils.py
pywren_ibm_cloud/version.py
pywren_ibm_cloud/cli/__init__.py
pywren_ibm_cloud/cli/cli.py
pywren_ibm_cloud/cli/utils.py
pywren_ibm_cloud/cli/runtime/__init__.py
pywren_ibm_cloud/cli/runtime/cli.py
pywren_ibm_cloud/cli/runtime/utils.py
pywren_ibm_cloud/compute/__init__.py
pywren_ibm_cloud/compute/compute.py
pywren_ibm_cloud/compute/utils.py
pywren_ibm_cloud/compute/backends/__init__.py
pywren_ibm_cloud/compute/backends/cloudrun/__init__.py
pywren_ibm_cloud/compute/backends/cloudrun/cloudrun.py
pywren_ibm_cloud/compute/backends/cloudrun/config.py
pywren_ibm_cloud/compute/backends/cloudrun/entry_point.py
pywren_ibm_cloud/compute/backends/docker/__init__.py
pywren_ibm_cloud/compute/backends/docker/config.py
pywren_ibm_cloud/compute/backends/docker/docker.py
pywren_ibm_cloud/compute/backends/docker/entry_point.py
pywren_ibm_cloud/compute/backends/ibm_cf/__init__.py
pywren_ibm_cloud/compute/backends/ibm_cf/config.py
pywren_ibm_cloud/compute/backends/ibm_cf/entry_point.py
pywren_ibm_cloud/compute/backends/ibm_cf/ibm_cf.py
pywren_ibm_cloud/compute/backends/knative/__init__.py
pywren_ibm_cloud/compute/backends/knative/config.py
pywren_ibm_cloud/compute/backends/knative/entry_point.py
pywren_ibm_cloud/compute/backends/knative/knative.py
pywren_ibm_cloud/compute/backends/localhost/__init__.py
pywren_ibm_cloud/compute/backends/localhost/config.py
pywren_ibm_cloud/compute/backends/localhost/localhost.py
pywren_ibm_cloud/compute/backends/openwhisk/__init__.py
pywren_ibm_cloud/compute/backends/openwhisk/config.py
pywren_ibm_cloud/compute/backends/openwhisk/entry_point.py
pywren_ibm_cloud/compute/backends/openwhisk/openwhisk.py
pywren_ibm_cloud/job/__init__.py
pywren_ibm_cloud/job/job.py
pywren_ibm_cloud/job/partitioner.py
pywren_ibm_cloud/job/serialize.py
pywren_ibm_cloud-1.7.3.dist-info/LICENSE
pywren_ibm_cloud-1.7.3.dist-info/METADATA
pywren_ibm_cloud-1.7.3.dist-info/WHEEL
pywren_ibm_cloud-1.7.3.dist-info/entry_points.txt
pywren_ibm_cloud-1.7.3.dist-info/top_level.txt
pywren_ibm_cloud-1.7.3.dist-info/RECORD
