Metadata-Version: 2.1
Name: pywren-ibm-cloud
Version: 1.7.3
Summary: Run many jobs over IBM Cloud
Home-page: https://github.com/pywren/pywren-ibm-cloud
Author: Gil Vernik
Author-email: gilv@il.ibm.com
License: UNKNOWN
Platform: UNKNOWN
Classifier: Development Status :: 5 - Production/Stable
Classifier: Intended Audience :: Developers
Classifier: Operating System :: OS Independent
Classifier: Natural Language :: English
Classifier: License :: OSI Approved :: Apache Software License
Classifier: Programming Language :: Python
Classifier: Programming Language :: Python :: 3
Classifier: Programming Language :: Python :: 3.5
Classifier: Programming Language :: Python :: 3.6
Classifier: Programming Language :: Python :: 3.7
Classifier: Programming Language :: Python :: 3.8
Requires-Python: >=3.5
Requires-Dist: Click
Requires-Dist: pandas
Requires-Dist: PyYAML
Requires-Dist: python-dateutil
Requires-Dist: pika (==0.13.1)
Requires-Dist: enum34
Requires-Dist: glob2
Requires-Dist: tqdm
Requires-Dist: lxml
Requires-Dist: tblib
Requires-Dist: docker
Requires-Dist: requests
Requires-Dist: seaborn
Requires-Dist: paramiko
Requires-Dist: matplotlib
Requires-Dist: kubernetes
Requires-Dist: ibm-cos-sdk
Requires-Dist: gcsfs
